nirum_wsgi.py
nirum_wsgi-0.3.0.dist-info/METADATA
nirum_wsgi-0.3.0.dist-info/RECORD
nirum_wsgi-0.3.0.dist-info/WHEEL
nirum_wsgi-0.3.0.dist-info/entry_points.txt
nirum_wsgi-0.3.0.dist-info/top_level.txt
