Metadata-Version: 2.1
Name: nirum-wsgi
Version: 0.3.0
Summary: Nirum services as WSGI apps
Home-page: https://github.com/spoqa/nirum-python-wsgi
Author: Nirum team
License: MIT license
Platform: UNKNOWN
Classifier: Development Status :: 4 - Beta
Classifier: Intended Audience :: Developers
Classifier: License :: OSI Approved :: MIT License
Classifier: Operating System :: OS Independent
Classifier: Programming Language :: Python :: 2.7
Classifier: Programming Language :: Python :: 3.4
Classifier: Programming Language :: Python :: 3.5
Classifier: Programming Language :: Python :: 3.6
Classifier: Topic :: Internet :: WWW/HTTP :: WSGI :: Application
Classifier: Topic :: Software Development :: Code Generators
Classifier: Topic :: Software Development :: Libraries :: Python Modules
Classifier: Topic :: Software Development :: Object Brokering
Provides-Extra: tests
Requires-Dist: nirum (>=0.6.3)
Requires-Dist: six
Requires-Dist: Werkzeug (<1.0,>=0.11)
Requires-Dist: typing; python_version<'3.5'
Provides-Extra: tests
Requires-Dist: flake8-import-order (<1.0,>=0.17.1); extra == 'tests'
Requires-Dist: flake8-import-order-spoqa (<2.0.0,>=1.4.0); extra == 'tests'
Requires-Dist: pycodestyle (<2.4.0); extra == 'tests'
Requires-Dist: pytest (<4.0.0,>=3.5.1); extra == 'tests'
Requires-Dist: pytest-flake8 (<1.1.0,>=1.0.1); extra == 'tests'
Requires-Dist: requests-mock (<1.6.0,>=1.5.0); extra == 'tests'
